clovers_core/__init__.py
clovers_core/adapter.py
clovers_core/config.py
clovers_core/plugin.py
clovers_core-0.1.1.dist-info/LICENSE
clovers_core-0.1.1.dist-info/METADATA
clovers_core-0.1.1.dist-info/WHEEL
clovers_core-0.1.1.dist-info/RECORD
