Metadata-Version: 2.1
Name: clovers-core
Version: 0.1.1
Summary: 
Author: KarisAya
Author-email: 1048827424@qq.com
Requires-Python: >=3.12,<4.0
Classifier: Programming Language :: Python :: 3
Requires-Dist: pydantic (>=2.5.3,<3.0.0)
Requires-Dist: toml (>=0.10.2,<0.11.0)
